{"extracted_information": "Sublist3r هي أداة سريعة لتعداد النطاقات الفرعية (subdomains) مصممة لمختبري الاختراق. تشمل ميزاتها استخدام حلول Subbrute لتحقيق التعداد، ودعم وضع التفاعل، والاستفادة من آليات الخيوط المتعددة (multi-threading) لتحسين الأداء. تم تطوير الأداة باستخدام بايثون.", "specifications": {}, "pricing": {}, "features": [{"name": "تعداد النطاقات الفرعية السريع", "description": "أداة متخصصة لتعداد النطاقات الفرعية بكفاءة وسرعة."}, {"name": "استخدام Subbrute", "description": "تعتمد على حلول Subbrute المحدثة في عملية التعداد."}, {"name": "وضع التفاعل (Interactive Mode)", "description": "توفر دعماً لوضع التفاعل للمستخدم."}, {"name": "الأداء المتعدد الخيوط (Multi-threading)", "description": "تستخدم آليات قفل الخيوط (thread locks) لتمكين المعالجة المتوازية وتحسين الأداء."}, {"name": "مبنية على بايثون", "description": "مكتوبة بلغة بايثون وتتطلب ملف requirements.txt لتثبيت الاعتمادات."}], "statistics": {}, "temporal_info": {"أحدث_تحديث_للمستودع": "يناير 5, 2020", "تاريخ_الالتزام_الأولي": "ديسمبر 15, 2015"}, "geographical_data": {}, "references": []}